{
  "exams": [
    {
      "rocYear": 113,
      "adYear": 2024,
      "examCode": "113110",
      "format": "new",
      "papers": [
        { "code": "301", "subjects": ["0101"], "name": "綜合法學(一)-憲法、行政法、國際公法、國際私法" },
        { "code": "302", "subjects": ["0301"], "name": "綜合法學(一)-刑法、刑事訴訟法、法律倫理" },
        { "code": "303", "subjects": ["0201"], "name": "綜合法學(二)-民法、民事訴訟法" },
        { "code": "304", "subjects": ["0202"], "name": "綜合法學(二)-公司法、保險法、票據法、證券交易法、強制執行法、法學英文" }
      ]
    },
    {
      "rocYear": 112,
      "adYear": 2023,
      "examCode": "112120",
      "format": "new",
      "papers": [
        { "code": "301", "subjects": ["0101"], "name": "綜合法學(一)-憲法、行政法、國際公法、國際私法" },
        { "code": "302", "subjects": ["0301"], "name": "綜合法學(一)-刑法、刑事訴訟法、法律倫理" },
        { "code": "303", "subjects": ["0201"], "name": "綜合法學(二)-民法、民事訴訟法" },
        { "code": "304", "subjects": ["0202"], "name": "綜合法學(二)-公司法、保險法、票據法、證券交易法、強制執行法、法學英文" }
      ]
    },
    {
      "rocYear": 111,
      "adYear": 2022,
      "examCode": "111120",
      "format": "new",
      "papers": [
        { "code": "301", "subjects": ["0101"], "name": "綜合法學(一)-憲法、行政法、國際公法、國際私法" },
        { "code": "302", "subjects": ["0301"], "name": "綜合法學(一)-刑法、刑事訴訟法、法律倫理" },
        { "code": "303", "subjects": ["0201"], "name": "綜合法學(二)-民法、民事訴訟法" },
        { "code": "304", "subjects": ["0202"], "name": "綜合法學(二)-公司法、保險法、票據法、證券交易法、強制執行法、法學英文" }
      ]
    },
    {
      "rocYear": 110,
      "adYear": 2021,
      "examCode": "110120",
      "format": "new",
      "papers": [
        { "code": "301", "subjects": ["0101"], "name": "綜合法學(一)-憲法、行政法、國際公法、國際私法" },
        { "code": "302", "subjects": ["0301"], "name": "綜合法學(一)-刑法、刑事訴訟法、法律倫理" },
        { "code": "303", "subjects": ["0201"], "name": "綜合法學(二)-民法、民事訴訟法" },
        { "code": "304", "subjects": ["0202"], "name": "綜合法學(二)-公司法、保險法、票據法、證券交易法、強制執行法、法學英文" }
      ]
    },
    {
      "rocYear": 109,
      "adYear": 2020,
      "examCode": "109120",
      "format": "new",
      "papers": [
        { "code": "301", "subjects": ["0101"], "name": "綜合法學(一)-憲法、行政法、國際公法、國際私法" },
        { "code": "302", "subjects": ["0301"], "name": "綜合法學(一)-刑法、刑事訴訟法、法律倫理" },
        { "code": "303", "subjects": ["0201"], "name": "綜合法學(二)-民法、民事訴訟法" },
        { "code": "304", "subjects": ["0202"], "name": "綜合法學(二)-公司法、保險法、票據法、證券交易法、強制執行法、法學英文" }
      ]
    }
  ]
}
